sungrowinverter/__init__.py
sungrowinverter/configs/__init.__.py
sungrowinverter/configs/common.py
sungrowinverter/configs/hybrid.py
sungrowinverter/configs/inverter.py
sungrowinverter/configs/string.py
sungrowinverter/SungrowInverter.py
sungrowinverter/SungrowModbusTCPClient.py
sungrowinverter-0.2.3.dist-info/LICENSE
sungrowinverter-0.2.3.dist-info/METADATA
sungrowinverter-0.2.3.dist-info/WHEEL
sungrowinverter-0.2.3.dist-info/RECORD
