Metadata-Version: 2.1
Name: sungrowinverter
Version: 0.2.3
Summary: Query Sungrow residential hybrid or string inverters for current state and statistics using ModBus TCP client
Home-page: https://github.com/mvandersteen/SungrowInverter
License: GNU General Public License
Author: Mark Vandersteen
Author-email: mark@vandersteen.me
Requires-Python: >=3.9,<4.0
Classifier: Development Status :: 4 - Beta
Classifier: Intended Audience :: Developers
Classifier: License :: OSI Approved :: GNU General Public License v3 (GPLv3)
Classifier: License :: Other/Proprietary License
Classifier: Programming Language :: Python :: 3
Classifier: Programming Language :: Python :: 3.9
Classifier: Programming Language :: Python :: 3.10
Classifier: Programming Language :: Python :: 3.11
Classifier: Programming Language :: Python :: 3
Classifier: Programming Language :: Python :: 3.10
Classifier: Programming Language :: Python :: 3.9
Classifier: Topic :: Software Development :: Libraries :: Python Modules
Classifier: Topic :: System :: Networking
Requires-Dist: pycryptodomex (>=3.11.0)
Requires-Dist: pymodbus (>=3.0.0)
Project-URL: Repository, https://github.com/mvandersteen/SungrowInverter
